[{"pk": 4, "model": "accounting.orderstate", "fields": {"description": "cancelled", "stateID": 3}}, {"pk": 6, "model": "accounting.orderstate", "fields": {"description": "character deleted", "stateID": 5}}, {"pk": 2, "model": "accounting.orderstate", "fields": {"description": "closed", "stateID": 1}}, {"pk": 3, "model": "accounting.orderstate", "fields": {"description": "expired (or fulfilled)", "stateID": 2}}, {"pk": 1, "model": "accounting.orderstate", "fields": {"description": "open/active", "stateID": 0}}, {"pk": 5, "model": "accounting.orderstate", "fields": {"description": "pending", "stateID": 4}}]
